bqspec/__init__.py
bqspec/__main__.py
bqspec/__version__.py
bqspec/bqtype.py
bqspec/cli.py
bqspec/error.py
bqspec/loader.py
bqspec/rcpath.py
bqspec/rstruct.py
bqspec/spec.py
bqspec/validator/__init__.py
bqspec/validator/schema.py
bqspec/validator/values.py
bqspec-0.3.3.dist-info/LICENSE
bqspec-0.3.3.dist-info/METADATA
bqspec-0.3.3.dist-info/WHEEL
bqspec-0.3.3.dist-info/entry_points.txt
bqspec-0.3.3.dist-info/top_level.txt
bqspec-0.3.3.dist-info/RECORD
