Metadata-Version: 2.1
Name: bqspec
Version: 0.3.3
Summary: SQL testing tool for Google BigQuery
Home-page: https://github.com/orisano/bqspec
Author: Nao YONASHIRO
Author-email: owan.orisano@gmail.com
License: MIT
Platform: UNKNOWN
Classifier: Development Status :: 2 - Pre-Alpha
Classifier: License :: OSI Approved :: MIT License
Classifier: Programming Language :: Python
Classifier: Programming Language :: Python :: 2.7
Classifier: Programming Language :: Python :: 3.6
Classifier: Programming Language :: Python :: 3.7
Classifier: Programming Language :: Python :: 3.8
Classifier: Programming Language :: Python :: Implementation :: CPython
Classifier: Topic :: Software Development :: Libraries
Classifier: Topic :: Software Development :: Libraries :: Python Modules
Classifier: Topic :: Utilities
Requires-Dist: six
Requires-Dist: ruamel.yaml
Requires-Dist: embexpr
Requires-Dist: google-cloud-bigquery (==0.25.0)
Requires-Dist: click
Requires-Dist: tqdm
